{
  "latest_version": "VN117",
  "release_time": "2026-07-20 15:47 CEST",
  "package_url": "https://github.com/piplupssss/EU-Retail-CWH-/releases/download/VN117/VN117_update.zip",
  "sha256": "ae0f8d375cd317b76b34d2eae1ee4a7a2c2ac76169039c42db3cccfd20ce6fc5",
  "notes": [
    "供应商 Stock List 刷新时，系统会按 Warehouse + Product No 对比旧库存和新库存，只释放已经被新库存快照吸收的确认出库占用。",
    "库存已经从 10 变为 2 时，原有 STT 确认出库的红色 -8 会自动关闭；库存仍为 1 时，未实际出库的红色 -1 会继续保留。",
    "支持部分吸收：需求或 STT 确认 8 件但新库存只下降 5 件时，系统保留剩余 -3，避免提前释放未完成出库。",
    "供应商库存导入和出入库通知继续保留 Stock List 中 Product No、Category、Category 2 的原始写法；更新包不包含本地数据库、图片或供应商上传文件。"
  ]
}